Metadata-Version: 2.1
Name: file-reloader
Version: 1.0.4
Summary: file-reloader allows user program to reload automatically when source code of user program changes
Author-email: Mohammad Ummair <mohdummair007@gmail.com>
License: BSD-3-Clause
Keywords: reloader,autoreload,file-reloader,code reloading,automatic refresh,development workflow,source code monitoring,Python productivity,efficient coding,file change detection,development environment,PyPI package,GitHub code reloader,streamlined development,time-saving coding,source code watcher,open-source reloader,continuous development,coding efficiency,automated code updates,developer productivity,project auto-reload,real-time code changes,dependency-free autoreloading,easy integration,s
Requires-Python: >=3.8
License-File: LICENSE
